innovate/__init__.py
innovate/backend.py
innovate/abm/__init__.py
innovate/abm/agent.py
innovate/abm/competitive_diffusion.py
innovate/abm/disruptive_innovation.py
innovate/abm/model.py
innovate/abm/ndlib_model.py
innovate/abm/sentiment_hype_cycle.py
innovate/adopt/__init__.py
innovate/adopt/categorization.py
innovate/backends/jax_backend.py
innovate/backends/numpy_backend.py
innovate/base/__init__.py
innovate/base/base.py
innovate/causal/__init__.py
innovate/causal/counterfactual.py
innovate/compete/__init__.py
innovate/compete/competition.py
innovate/compete/lotka_volterra.py
innovate/compete/multi_product.py
innovate/data/oecd.py
innovate/diffuse/__init__.py
innovate/diffuse/bass.py
innovate/diffuse/gompertz.py
innovate/diffuse/logistic.py
innovate/dynamics/__init__.py
innovate/dynamics/base.py
innovate/dynamics/competition.py
innovate/dynamics/contagion.py
innovate/dynamics/system.py
innovate/dynamics/competition/__init__.py
innovate/dynamics/competition/base.py
innovate/dynamics/competition/lotka_volterra.py
innovate/dynamics/competition/market_share_attraction.py
innovate/dynamics/competition/replicator_dynamics.py
innovate/dynamics/contagion/__init__.py
innovate/dynamics/contagion/base.py
innovate/dynamics/contagion/seir.py
innovate/dynamics/contagion/sir.py
innovate/dynamics/contagion/sis.py
innovate/dynamics/growth/__init__.py
innovate/dynamics/growth/base.py
innovate/dynamics/growth/dual_influence.py
innovate/dynamics/growth/skewed.py
innovate/dynamics/growth/symmetric.py
innovate/dynamics/system/__init__.py
innovate/dynamics/system/base.py
innovate/dynamics/system/hype_cycle.py
innovate/ecosystem/complementary_goods.py
innovate/ecosystems/co_evolution.py
innovate/ecosystems/platform_multi_sided_growth.py
innovate/fail/analysis.py
innovate/fitters/__init__.py
innovate/fitters/batched_fitter.py
innovate/fitters/bayesian_fitter.py
innovate/fitters/blackjax_fitter.py
innovate/fitters/bootstrap_fitter.py
innovate/fitters/curve_fitter.py
innovate-0.5.0.dist-info/licenses/LICENSE
innovate-0.5.0.dist-info/METADATA
innovate-0.5.0.dist-info/WHEEL
innovate-0.5.0.dist-info/top_level.txt
innovate-0.5.0.dist-info/RECORD
