Metadata-Version: 2.4
Name: innovate
Version: 0.5.0
Summary: A Python library for simplifying innovation/policy diffusion modelling.
Author-email: Dylan A Mordaunt <dylan.mordaunt@vuw.ac.nz>
License-Expression: Apache-2.0
Project-URL: Homepage, https://github.com/edithatogo/innovate
Project-URL: Documentation, https://edithatogo.github.io/innovate
Requires-Python: >=3.8
License-File: LICENSE
Requires-Dist: numpy
Requires-Dist: scipy
Requires-Dist: pandas
Requires-Dist: statsmodels
Requires-Dist: pyarrow
Requires-Dist: jitcdde
Requires-Dist: mesa
Requires-Dist: networkx
Requires-Dist: ruptures
Requires-Dist: pymannkendall
Requires-Dist: typing_extensions
Requires-Dist: pytensor
Requires-Dist: ndlib
Provides-Extra: jax
Requires-Dist: jax>=0.4.20; extra == "jax"
Requires-Dist: jaxlib>=0.4.20; extra == "jax"
Requires-Dist: numpyro>=0.13.2; extra == "jax"
Requires-Dist: scipy>=1.9; extra == "jax"
Requires-Dist: numpy<3; extra == "jax"
Requires-Dist: diffrax; extra == "jax"
Requires-Dist: jaxopt; extra == "jax"
Requires-Dist: blackjax; extra == "jax"
Requires-Dist: arviz; extra == "jax"
Provides-Extra: dev
Requires-Dist: pytest; extra == "dev"
Requires-Dist: ruff; extra == "dev"
Requires-Dist: pre-commit; extra == "dev"
Requires-Dist: mypy; extra == "dev"
Requires-Dist: bandit; extra == "dev"
Dynamic: license-file
